{
  "forms_list": [
    "건축직",
    "경력직(기계)",
    "경력직(기계_안전)",
    "경력직(전기)",
    "경력직(토목)",
    "경력직(행정)",
    "경력직(행정)_기록물",
    "경력직(환경)",
    "경력직(환경)_6급",
    "경비",
    "경비)",
    "공무직(UIS)",
    "공무직(관로)",
    "공무직(관리사무소장)",
    "공무직(도로청소",
    "공무직(미화)",
    "공무직(비서)",
    "공무직(승강장안전문 유지보수)",
    "공무직(시설관리",
    "공무직(시설관리)",
    "공무직(시설관리_공통)",
    "공무직(시설관리_매립)",
    "공무직(시설관리_운전)",
    "공무직(시설관리_전기)",
    "공무직(시설관리_통신)",
    "공무직(시설관리원_운전)",
    "공무직(시설운영)",
    "공무직(안내)",
    "공무직(영양사)",
    "공무직(운전)",
    "공무직(운전_장애)",
    "공무직(운전경력)",
    "공무직(운전고졸)",
    "공무직(운전원)",
    "공무직(운전장애)",
    "공무직(장례지도",
    "공무직(전기설비 유지보수)",
    "공무직(조경)",
    "공무직(차량중정비)",
    "공무직(해설)",
    "공무직_경비원",
    "공무직_미화원",
    "공무직_비서",
    "공무직_시설운영원",
    "공무직_운전원",
    "관리요원)",
    "기계직",
    "녹지직",
    "도로순찰",
    "도로청소",
    "모집부문-정규직",
    "무기계약직",
    "무기계약직(시설관리",
    "보훈(기계)",
    "보훈(전기)",
    "보훈(행정)",
    "복지매니저",
    "복지매니저(상담)",
    "복지매니저(장애인))",
    "복지매니저)",
    "사무보조원(UIS)",
    "시설관리",
    "시설관리(경력)",
    "시설관리원(운전)",
    "식당조리",
    "식당조리(경력)",
    "식당조리)",
    "신호직",
    "심판보조원)",
    "아르피나 운영직",
    "아르피나 운영직 8급_통합프런트(기능인재)",
    "아르피나 운영직(기능인재)",
    "운영직",
    "운영직(발매원",
    "운영직(시설운영)",
    "운영직(전산)",
    "운영직(청소년 지도사)",
    "운전직",
    "일반계약직",
    "일반계약직3명",
    "일반사무직",
    "일반직 3명",
    "일반직(기계)",
    "일반직(기계)_고졸기능인재",
    "일반직(기계_안전)",
    "일반직(기계_에너지관리)",
    "일반직(시설)",
    "일반직(전기)",
    "일반직(전기)_고졸",
    "일반직(전산)",
    "일반직(토목)",
    "일반직(행정)",
    "일반직(환경)",
    "일용계약직3명",
    "장례지도",
    "장례지도)",
    "장례직",
    "장애인(기계)",
    "장애인(전기)",
    "장애인(행정)",
    "장애인(환경)",
    "전기직",
    "전문계약직1명",
    "전산직",
    "전산직(경력)",
    "조경직",
    "직급-무기계약직",
    "청년인턴(계약수납업무)",
    "청년인턴(보상업무)",
    "청년인턴(상가)",
    "청년인턴(수납)",
    "청년인턴(영구임대)",
    "청년인턴(임대업무)",
    "청년인턴(임대주택)",
    "청년인턴(장애인_임대업무)",
    "청년인턴(행복주택)",
    "청소",
    "청소)",
    "체험형 인턴(1·2기)",
    "체험형 청년인턴",
    "체험형인턴",
    "토목직",
    "통신직",
    "행정직",
    "행정직(경력)",
    "행정직_기록물관리",
    "행정직_장애인"
  ],
  "forms_by_organization": {
    "부산교통공사": [
      "운영직",
      "운전직",
      "토목직",
      "건축직",
      "기계직",
      "전기직",
      "신호직",
      "통신직",
      "공무직(차량중정비)",
      "공무직(전기설비 유지보수)",
      "체험형 인턴(1·2기)",
      "공무직(승강장안전문 유지보수)"
    ],
    "부산도시공사": [
      "공무직(비서)",
      "공무직(안내)",
      "공무직(운전)",
      "행정직",
      "건축직",
      "전기직",
      "통신직",
      "공무직(관리사무소장)",
      "공무직(시설관리_전기)",
      "공무직(시설관리_통신)",
      "공무직(시설관리_공통)",
      "공무직(미화)",
      "토목직",
      "행정직_장애인",
      "공무직(운전원)",
      "전산직",
      "조경직",
      "기계직",
      "운영직(청소년 지도사)",
      "운영직(전산)",
      "운영직(시설운영)",
      "공무직(시설운영)",
      "체험형 청년인턴",
      "공무직_시설운영원",
      "공무직_경비원",
      "아르피나 운영직 8급_통합프런트(기능인재)",
      "청년인턴(임대업무)",
      "청년인턴(계약수납업무)",
      "청년인턴(보상업무)",
      "청년인턴(장애인_임대업무)",
      "행정직_기록물관리",
      "공무직_운전원",
      "공무직_비서",
      "아르피나 운영직",
      "청년인턴(임대주택)",
      "청년인턴(상가)",
      "공무직_미화원",
      "아르피나 운영직(기능인재)",
      "청년인턴(영구임대)",
      "청년인턴(수납)",
      "청년인턴(행복주택)"
    ],
    "부산시설공단": [
      "행정직",
      "행정직(경력)",
      "기계직",
      "전기직",
      "토목직",
      "건축직",
      "통신직",
      "전산직(경력)",
      "무기계약직(시설관리",
      "도로청소",
      "청소)",
      "공무직(시설관리",
      "청소",
      "경비)",
      "공무직(도로청소",
      "복지매니저",
      "장례지도",
      "녹지직",
      "공무직(장례지도",
      "시설관리",
      "경비",
      "식당조리)",
      "도로순찰",
      "식당조리(경력)",
      "복지매니저(장애인))",
      "복지매니저(상담)",
      "시설관리(경력)",
      "운영직(발매원",
      "관리요원)",
      "식당조리",
      "장례지도)",
      "장례직",
      "심판보조원)",
      "복지매니저)",
      "전산직"
    ],
    "부산환경공단": [
      "일반직(행정)",
      "일반직(기계)",
      "일반직(전기)",
      "일반직(환경)",
      "일반직(토목)",
      "일반직(시설)",
      "경력직(행정)",
      "경력직(기계)",
      "경력직(기계_안전)",
      "경력직(전기)",
      "경력직(환경)",
      "경력직(토목)",
      "장애인(행정)",
      "장애인(환경)",
      "보훈(기계)",
      "보훈(전기)",
      "시설관리원(운전)",
      "사무보조원(UIS)",
      "장애인(기계)",
      "일반직(기계_에너지관리)",
      "공무직(시설관리원_운전)",
      "경력직(환경)_6급",
      "일반직(전기)_고졸",
      "경력직(행정)_기록물",
      "장애인(전기)",
      "일반직(기계_안전)",
      "공무직(시설관리)",
      "일반직(전산)",
      "공무직(시설관리_매립)",
      "공무직(시설관리_운전)",
      "일반직(기계)_고졸기능인재",
      "공무직(관로)",
      "공무직(운전)",
      "공무직(영양사)",
      "공무직(운전_장애)",
      "공무직(조경)",
      "공무직(UIS)",
      "공무직(해설)",
      "보훈(행정)",
      "공무직(운전경력)",
      "공무직(운전장애)",
      "공무직(운전고졸)"
    ],
    "부산관광공사": [
      "일반계약직",
      "무기계약직",
      "일반계약직3명",
      "일용계약직3명",
      "일반직 3명",
      "전문계약직1명",
      "일반사무직",
      "모집부문-정규직",
      "직급-무기계약직",
      "체험형인턴",
      "체험형 청년인턴"
    ]
  }
}